persepolis_lib/__init__.py
persepolis_lib/persepolis_lib.py
persepolis_lib/useful_tools.py
persepolis_lib-1.1.2.dist-info/METADATA
persepolis_lib-1.1.2.dist-info/WHEEL
persepolis_lib-1.1.2.dist-info/licenses/LICENSE
persepolis_lib-1.1.2.dist-info/RECORD
