Metadata-Version: 2.4
Name: persepolis_lib
Version: 1.1.2
Summary: A Python library for easier and faster downloading.
Project-URL: Homepage, https://github.com/persepolisdm/persepolis_lib
Project-URL: Documentation, https://github.com/persepolisdm/persepolis_lib/README.md
Project-URL: Repository, https://github.com/persepolisdm/persepolis_lib
Project-URL: Issues, https://github.com/persepolisdm/persepolis_lib/issues
Author-email: AliReza AmirSamimi <alireza.amirsamimi@gmail.com>
Maintainer-email: AliReza AmirSamimi <alireza.amirsamimi@gmail.com>
License:                     GNU GENERAL PUBLIC LICENSE
License-File: LICENSE
Keywords: download manager,persepolis,persepolis_lib
Classifier: Development Status :: 5 - Production/Stable
Classifier: Programming Language :: Python
Requires-Python: >=3.5
Requires-Dist: psutil
Requires-Dist: pysocks
Requires-Dist: requests
Requires-Dist: urllib3
